ENPMDATests/__init__.py
ENPMDATests/datafiles.py
ENPMDATests/test_ENPMDA.py
ENPMDATests/datafile/ensemble_AlaDipeptide/rep1/md.tpr
ENPMDATests/datafile/ensemble_AlaDipeptide/rep1/md.xtc
ENPMDATests/datafile/ensemble_AlaDipeptide/rep1/start.pdb
ENPMDATests/datafile/ensemble_AlaDipeptide/rep2/md.tpr
ENPMDATests/datafile/ensemble_AlaDipeptide/rep2/md.xtc
ENPMDATests/datafile/ensemble_AlaDipeptide/rep2/start.pdb
ENPMDATests/datafile/ensemble_AlaDipeptide/rep3/md.tpr
ENPMDATests/datafile/ensemble_AlaDipeptide/rep3/md.xtc
ENPMDATests/datafile/ensemble_AlaDipeptide/rep3/start.pdb
ENPMDATests/datafile/ensemble_AlaDipeptide/rep4/md.tpr
ENPMDATests/datafile/ensemble_AlaDipeptide/rep4/md.xtc
ENPMDATests/datafile/ensemble_AlaDipeptide/rep4/start.pdb
ENPMDATests/datafile/ensemble_AlaDipeptide/rep5/md.tpr
ENPMDATests/datafile/ensemble_AlaDipeptide/rep5/md.xtc
ENPMDATests/datafile/ensemble_AlaDipeptide/rep5/start.pdb
ENPMDATests/datafile/ensemble_AlaDipeptide/rep6/md.tpr
ENPMDATests/datafile/ensemble_AlaDipeptide/rep6/md.xtc
ENPMDATests/datafile/ensemble_AlaDipeptide/rep6/start.pdb
ENPMDATests/datafile/ensemble_AlaDipeptide/rep7/md.tpr
ENPMDATests/datafile/ensemble_AlaDipeptide/rep7/md.xtc
ENPMDATests/datafile/ensemble_AlaDipeptide/rep7/start.pdb
ENPMDATests/datafile/ensemble_AlaDipeptide/rep8/md.tpr
ENPMDATests/datafile/ensemble_AlaDipeptide/rep8/md.xtc
ENPMDATests/datafile/ensemble_AlaDipeptide/rep8/start.pdb
enpmdatests-1.1.1.dist-info/METADATA
enpmdatests-1.1.1.dist-info/WHEEL
enpmdatests-1.1.1.dist-info/top_level.txt
enpmdatests-1.1.1.dist-info/RECORD
