Metadata-Version: 2.4
Name: ENPMDATests
Version: 1.1.1
Summary: test for parallel analysis for ensemble simulations
Home-page: https://github.com/yuxuanzhuang/ENPMDA
Author: Yuxuan Zhuang
Author-email: yuxuan.zhuang@dbb.su.se
License: GNU General Public License v3
Classifier: Development Status :: 2 - Pre-Alpha
Classifier: Intended Audience :: Developers
Classifier: License :: OSI Approved :: GNU General Public License v3 (GPLv3)
Classifier: Natural Language :: English
Classifier: Programming Language :: Python :: 3
Classifier: Programming Language :: Python :: 3.6
Classifier: Programming Language :: Python :: 3.7
Classifier: Programming Language :: Python :: 3.8
Requires-Python: >=3.6
Requires-Dist: pytest>=3.3.0
Requires-Dist: hypothesis
Dynamic: author
Dynamic: author-email
Dynamic: classifier
Dynamic: description
Dynamic: home-page
Dynamic: license
Dynamic: requires-dist
Dynamic: requires-python
Dynamic: summary
